[
    {
        "id": 100,
        "title": "New 7 Wonders of the World",
        "url": "https://world.new7wonders.com/",
        "wonders": [
            {
                "id": 101,
                "title": "Chichén Itzá, Mexico",
                "url": "https://world.new7wonders.com/wonders/pyramid-at-chichen-itza-before-800-a-d-yucatan-peninsula-mexico/",
                "whs": 483
            },
            {
                "id": 102,
                "title": "Christ the Redeemer, Rio de Janeiro, Brazil",
                "url": "https://world.new7wonders.com/wonders/christ-redeemer-1931-rio-de-janeiro-brazil/",
                "whs": 1100
            },
            {
                "id": 103,
                "title": "Colosseum, Rome, Italy",
                "url": "https://world.new7wonders.com/wonders/roman-colosseum-70-82-a-d-rome-italy/",
                "whs": 91
            },
            {
                "id": 104,
                "title": "Great Wall of China",
                "url": "https://world.new7wonders.com/wonders/great-wall-of-china-220-b-c-and-1368-1644-a-d-china/",
                "whs": 438
            },
            {
                "id": 105,
                "title": "Machu Picchu, Peru",
                "url": "https://world.new7wonders.com/wonders/machu-picchu-1460-1470-peru/",
                "whs": 274
            },
            {
                "id": 106,
                "title": "Petra, Jordan",
                "url": "https://world.new7wonders.com/wonders/petra-9-b-c-40-a-d-jordan/",
                "whs": 326
            },
            {
                "id": 107,
                "title": "Taj Mahal, Agra, India",
                "url": "https://world.new7wonders.com/wonders/taj-mahal-1630-a-d-agra-india/",
                "whs": 252
            }
        ],
        "finalists": [
            {
                "id": 108,
                "title": "Angkor Wat, Cambodia",
                "url": "https://world.new7wonders.com/wonders/angkor-12th-century-cambodia/",
                "whs": 668
            },
            {
                "id": 109,
                "title": "Acropolis of Athens, Greece",
                "url": "https://world.new7wonders.com/wonders/acropolis-of-athens-450-330-b-c-athens-greece/",
                "whs": 404
            },
            {
                "id": 110,
                "title": "Alhambra, Granada, Spain",
                "url": "https://world.new7wonders.com/wonders/alhambra-12th-century-granada-spain/",
                "whs": 314
            },
            {
                "id": 111,
                "title": "Eiffel Tower, Paris, France",
                "url": "https://world.new7wonders.com/wonders/eiffel-tower-1887-89-paris-france/",
                "whs": 600
            },
            {
                "id": 112,
                "title": "Giza Pyramids, Egypt",
                "url": "https://world.new7wonders.com/wonders/pyramids-of-giza-2600-2500-b-c-egypt/",
                "whs": 86
            },
            {
                "id": 113,
                "title": "Hagia Sophia, Istanbul, Turkey",
                "url": "https://world.new7wonders.com/wonders/hagia-sophia-532-537-a-d-istanbul-turkey/",
                "whs": 356
            },
            {
                "id": 114,
                "title": "Kiyomizu-dera, Kyoto, Japan",
                "url": "https://world.new7wonders.com/wonders/kiyomizu-temple-749-1855-kyoto-japan/",
                "whs": 688
            },
            {
                "id": 115,
                "title": "Kremlin and Red Square, Moscow, Russia",
                "url": "https://world.new7wonders.com/wonders/kremlin-and-red-square-1156-1850-moscow-russia/",
                "whs": 545
            },
            {
                "id": 116,
                "title": "Moai Statues, Easter Island, Chile",
                "url": "https://world.new7wonders.com/wonders/statues-of-easter-island-10th-16th-century-easter-island-chile/",
                "whs": 715
            },
            {
                "id": 117,
                "title": "Neuschwanstein Castle, Hohenschwangau, Germany",
                "url": "https://world.new7wonders.com/wonders/neuschwanstein-castle-1869-1884-schwangau-germany/",
                "twhs": 5983
            },
            {
                "id": 118,
                "title": "Statue of Liberty, New York, USA",
                "url": "https://world.new7wonders.com/wonders/statue-of-liberty-1886-new-york-city-u-s-a/",
                "whs": 307
            },
            {
                "id": 119,
                "title": "Stonehenge, Wiltshire, UK",
                "url": "https://world.new7wonders.com/wonders/stonehenge-3000-b-c-1600-b-c-amesbury-united-kingdom/",
                "whs": 373
            },
            {
                "id": 120,
                "title": "Sydney Opera House, Australia",
                "url": "https://world.new7wonders.com/wonders/sydney-opera-house-1954-73-sydney-australia/",
                "whs": 166
            },
            {
                "id": 121,
                "title": "Timbuktu, Mali",
                "url": "https://world.new7wonders.com/wonders/timbuktu-12th-century-mali/",
                "whs": 119
            }
        ]
    },
    {
        "id": 200,
        "title": "New 7 Wonders of Nature",
        "url": "https://nature.new7wonders.com/",
        "wonders": [
            {
                "id": 201,
                "title": "Amazon, Peru/Colombia/Brazil",
                "url": "https://nature.new7wonders.com/wonders/amazon-south-america/",
                "whs": 998
            },
            {
                "id": 202,
                "title": "Hạ Long Bay, Vietnam",
                "url": "https://nature.new7wonders.com/wonders/ha-long-bay-vietnam/",
                "whs": 672
            },
            {
                "id": 203,
                "title": "Iguazu Falls, Argentina/Brazil",
                "url": "https://nature.new7wonders.com/wonders/iguazu-falls-argentina-and-brazil/",
                "whs": 355
            },
            {
                "id": 204,
                "title": "Jeju Island, South Korea",
                "url": "https://nature.new7wonders.com/wonders/jeju-island-korea-south/",
                "whs": 1264
            },
            {
                "id": 205,
                "title": "Komodo Island, Indonesia",
                "url": "https://nature.new7wonders.com/wonders/komodo-indonesia/",
                "whs": 609
            },
            {
                "id": 206,
                "title": "Puerto Princesa Underground River, Philippines",
                "url": "https://nature.new7wonders.com/wonders/puerto-princessa-underground-river-philippines/",
                "whs": 652
            },
            {
                "id": 207,
                "title": "Table Mountain, Cape Town, South Africa",
                "url": "https://nature.new7wonders.com/wonders/table-mountain-south-africa/",
                "whs": 1007
            }
        ],
        "finalists": [
            {
                "id": 208,
                "title": "Angel Falls, Venezuela",
                "url": "https://nature.new7wonders.com/wonders/angel-falls-venezuela",
                "whs": 701
            },
            {
                "id": 209,
                "title": "Bay of Fundy, Canada/USA",
                "url": "https://nature.new7wonders.com/wonders/bay-of-fundy-canada",
                "whs": 1285
            },
            {
                "id": 210,
                "title": "Black Forest, Germany",
                "url": "https://nature.new7wonders.com/wonders/black-forest-germany/"
            },
            {
                "id": 211,
                "title": "Bu Tinah Shoals, United Arab Emirates",
                "url": "https://nature.new7wonders.com/wonders/bu-tinah-island-united-arab-emirates/",
                "twhs": 5661
            },
            {
                "id": 212,
                "title": "Cliffs of Moher, County Clare, Ireland",
                "url": "https://nature.new7wonders.com/wonders/cliffs-of-moher-ireland/",
                "twhs": 5522
            },
            {
                "id": 213,
                "title": "Dead Sea, Jordan/Israel/Palestine",
                "url": "https://nature.new7wonders.com/wonders/dead-sea-israel-jordan-palestine/",
                "twhs": 5158
            },
            {
                "id": 214,
                "title": "El Yunque, Puerto Rico",
                "url": "https://nature.new7wonders.com/wonders/el-yunque-puerto-rico/",
                "whs": 266
            },
            {
                "id": 215,
                "title": "Galápagos Archipiélago",
                "url": "https://nature.new7wonders.com/wonders/galapagos-ecuador/",
                "whs": 1
            },
            {
                "id": 216,
                "title": "Gobustan Mud Volcanoes, Azerbaijan",
                "url": "https://nature.new7wonders.com/wonders/mud-volcanoes-azerbaijan/",
                "whs": 1076
            },
            {
                "id": 217,
                "title": "Grand Canyon, USA",
                "url": "https://nature.new7wonders.com/wonders/grand-canyon-usa/",
                "whs": 75
            },
            {
                "id": 218,
                "title": "Great Barrier Reef, Australia",
                "url": "https://nature.new7wonders.com/wonders/great-barrier-reef-australia-papua-new-guinea/",
                "whs": 154
            },
            {
                "id": 219,
                "title": "Jeita Grotto, Lebanon",
                "url": "https://nature.new7wonders.com/wonders/jeita-grotto-lebanon/",
                "twhs": 405
            },
            {
                "id": 220,
                "title": "Kilimanjaro Region, Tanzania",
                "url": "https://nature.new7wonders.com/wonders/kilimanjaro-tanzania/",
                "whs": 403
            },
            {
                "id": 221,
                "title": "Maldives",
                "url": "https://nature.new7wonders.com/wonders/islands-of-the-maldives/",
                "twhs": 5812
            },
            {
                "id": 222,
                "title": "Masurian Lake District",
                "url": "https://nature.new7wonders.com/wonders/masurian-lake-district-poland/",
                "whs": 835
            },
            {
                "id": 223,
                "title": "Matterhorn, Switzerland/Italy",
                "url": "https://nature.new7wonders.com/wonders/matterhorn-cervino-italy-switzerland/",
                "whs": 1037
            },
            {
                "id": 224,
                "title": "Milford Sound, New Zealand",
                "url": "https://nature.new7wonders.com/wonders/milford-sound-new-zealand/",
                "whs": 551
            },
            {
                "id": 225,
                "title": "Sundarbans, Bangladesh/India",
                "url": "https://nature.new7wonders.com/wonders/sunderbans-bangladesh-india/",
                "whs": 798
            },
            {
                "id": 226,
                "title": "Uluru, Australia",
                "url": "https://nature.new7wonders.com/wonders/uluru-australia/",
                "whs": 447
            },
            {
                "id": 227,
                "title": "Vesuvius, Italy",
                "url": "https://nature.new7wonders.com/wonders/vesuvius-italy/",
                "whs": 829
            },
            {
                "id": 228,
                "title": "Yushan, Taiwan",
                "url": "https://nature.new7wonders.com/wonders/yushan-chinese-taipei/",
                "link": "http://english.moc.gov.tw/article/index.php?sn=1090"
            }
        ]
    },
    {
        "id": 300,
        "title": "New 7 Wonders Cities",
        "url": "https://cities.new7wonders.com/",
        "wonders": [
            {
                "id": 301,
                "title": "Beirut, Lebanon",
                "url": "https://cities.new7wonders.com/wonders/beirut-lebanon/"
            },
            {
                "id": 302,
                "title": "Doha, Qatar",
                "url": "https://cities.new7wonders.com/wonders/doha-qatar/",
                "twhs": 5317
            },
            {
                "id": 303,
                "title": "Durban, South Africa",
                "url": "https://cities.new7wonders.com/wonders/durban-south-africa/",
                "whs": 914
            },
            {
                "id": 304,
                "title": "Havana, Cuba",
                "url": "https://cities.new7wonders.com/wonders/havana-cuba/",
                "whs": 204
            },
            {
                "id": 305,
                "title": "Kuala Lumpur, Malaysia",
                "url": "https://cities.new7wonders.com/wonders/kuala-lumpur/",
                "twhs": 6175
            },
            {
                "id": 306,
                "title": "La Paz, Bolivia",
                "url": "https://cities.new7wonders.com/wonders/la-paz-bolivia/",
                "whs": 567
            },
            {
                "id": 307,
                "title": "Vigan, Philippines",
                "url": "https://cities.new7wonders.com/wonders/vigan-philippines/",
                "whs": 502
            }
        ],
        "finalists": [
            {
                "id": 308,
                "title": "Athens, Greece",
                "url": "https://cities.new7wonders.com/wonders/athens/"
            },
            {
                "id": 309,
                "title": "Bangkok, Thailand",
                "url": "https://cities.new7wonders.com/wonders/bangkok/",
                "whs": 576
            },
            {
                "id": 310,
                "title": "Barcelona, Spain",
                "url": "https://cities.new7wonders.com/wonders/barcelona/",
                "whs": 320
            },
            {
                "id": 311,
                "title": "Casablanca, Morocco",
                "url": "https://cities.new7wonders.com/wonders/casablanca/",
                "twhs": 5848
            },
            {
                "id": 312,
                "title": "Chicago, USA",
                "url": "https://cities.new7wonders.com/wonders/chicago/",
                "twhs": 5249
            },
            {
                "id": 313,
                "title": "Ho Chi Minh City, Vietnam",
                "url": "https://cities.new7wonders.com/wonders/ho-chi-minh-city/",
                "twhs": 5070
            },
            {
                "id": 314,
                "title": "Istanbul, Turkey",
                "url": "https://cities.new7wonders.com/wonders/istanbul/",
            },
            {
                "id": 315,
                "title": "Kyoto, Japan",
                "url": "https://cities.new7wonders.com/wonders/kyoto/",
            },
            {
                "id": 316,
                "title": "London, UK",
                "url": "https://cities.new7wonders.com/wonders/london/",
                "whs": 488
            },
            {
                "id": 317,
                "title": "Mendoza, Argentina",
                "url": "https://cities.new7wonders.com/wonders/mendoza/",
                "twhs": 2021
            },
            {
                "id": 318,
                "title": "Mexico City, Mexico",
                "url": "https://cities.new7wonders.com/wonders/mexico-city/",
                "whs": 412
            },
            {
                "id": 319,
                "title": "Mumbai, India",
                "url": "https://cities.new7wonders.com/wonders/mumbai/",
                "whs": 945
            },
            {
                "id": 320,
                "title": "Perth, Australia",
                "url": "https://cities.new7wonders.com/wonders/perth/",
                "whs": 578
            },
            {
                "id": 321,
                "title": "Phnom Penh, Cambodia",
                "url": "https://cities.new7wonders.com/wonders/phnom-penh/",
                "twhs": 65
            },
            {
                "id": 322,
                "title": "Prague, Czech Republic",
                "url": "https://cities.new7wonders.com/wonders/prague/",
                "whs": 616
            },
            {
                "id": 323,
                "title": "Quito, Ecuador",
                "url": "https://cities.new7wonders.com/wonders/quito/",
                "whs": 2
            },
            {
                "id": 324,
                "title": "Reykjavík, Iceland",
                "url": "https://cities.new7wonders.com/wonders/reykjavik/",
                "twhs": 5589
            },
            {
                "id": 325,
                "title": "Saint Petersburg, Russia",
                "url": "https://cities.new7wonders.com/wonders/saint-petersburg/",
                "whs": 540
            },
            {
                "id": 326,
                "title": "Seoul, South Korea",
                "url": "https://cities.new7wonders.com/wonders/seoul/",
                "whs": 816
            },
            {
                "id": 327,
                "title": "Shenzhen, China",
                "url": "https://cities.new7wonders.com/wonders/shenzhen/",
                "whs": 1110
            },
            {
                "id": 328,
                "title": "Vancouver, Canada",
                "url": "https://cities.new7wonders.com/wonders/vancouver/",
                "whs": 151
            }
        ]
    }
]